nopdb/__init__.py
nopdb/breakpoint.py
nopdb/call_capture.py
nopdb/common.py
nopdb/nice_debugger.py
nopdb/nopdb.py
nopdb/scope.py
nopdb-0.2.0.dist-info/LICENSE
nopdb-0.2.0.dist-info/WHEEL
nopdb-0.2.0.dist-info/METADATA
nopdb-0.2.0.dist-info/RECORD
